debug_helpers/__init__.py
debug_helpers/main.py
debug_helpers/print.py
debug_helpers-0.4.2.dist-info/METADATA
debug_helpers-0.4.2.dist-info/WHEEL
debug_helpers-0.4.2.dist-info/licenses/LICENSE
debug_helpers-0.4.2.dist-info/RECORD
