Metadata-Version: 2.4
Name: debug-helpers
Version: 0.4.2
Summary: 一个简单的 Python 调试辅助工具包
Project-URL: Homepage, https://github.com/jssfy/python_debug_helpers
Project-URL: Repository, https://github.com/jssfy/python_debug_helpers
Project-URL: Issues, https://github.com/jssfy/python_debug_helpers/issues
Author-email: Example Author <309228933@qq.com>
License: MIT
License-File: LICENSE
Classifier: Development Status :: 3 - Alpha
Classifier: Intended Audience :: Developers
Classifier: License :: OSI Approved :: MIT License
Classifier: Programming Language :: Python :: 3
Classifier: Programming Language :: Python :: 3.9
Classifier: Programming Language :: Python :: 3.10
Classifier: Programming Language :: Python :: 3.11
Classifier: Programming Language :: Python :: 3.12
Classifier: Programming Language :: Python :: 3.13
Requires-Python: >=3.9
Provides-Extra: dev
Requires-Dist: pytest-cov>=4.0.0; extra == 'dev'
Requires-Dist: pytest>=7.0.0; extra == 'dev'
